pmc_xml/__init__.py
pmc_xml/version.json
pmc_xml/bin/__init__.py
pmc_xml/bin/main.py
pmc_xml/core/__init__.py
pmc_xml/core/abstract.py
pmc_xml/core/article.py
pmc_xml/core/body.py
pmc_xml/core/parser.py
pmc_xml/util/__init__.py
pmc_xml-1.0.3.dist-info/METADATA
pmc_xml-1.0.3.dist-info/WHEEL
pmc_xml-1.0.3.dist-info/entry_points.txt
pmc_xml-1.0.3.dist-info/top_level.txt
pmc_xml-1.0.3.dist-info/RECORD
